extended_json_schema_validator/__init__.py
extended_json_schema_validator/__main__.py
extended_json_schema_validator/draw_schemas.py
extended_json_schema_validator/extend_validator_helpers.py
extended_json_schema_validator/extensible_validator.py
extended_json_schema_validator/py.typed
extended_json_schema_validator/extensions/__init__.py
extended_json_schema_validator/extensions/abstract_check.py
extended_json_schema_validator/extensions/fk_check.py
extended_json_schema_validator/extensions/index_check.py
extended_json_schema_validator/extensions/join_check.py
extended_json_schema_validator/extensions/pk_check.py
extended_json_schema_validator/extensions/unique_check.py
extended_json_schema_validator-0.15.3.data/scripts/jsonValidate.py
extended_json_schema_validator-0.15.3.dist-info/LICENSE
extended_json_schema_validator-0.15.3.dist-info/METADATA
extended_json_schema_validator-0.15.3.dist-info/WHEEL
extended_json_schema_validator-0.15.3.dist-info/entry_points.txt
extended_json_schema_validator-0.15.3.dist-info/top_level.txt
extended_json_schema_validator-0.15.3.dist-info/RECORD
