Metadata-Version: 2.1
Name: extended-json-schema-validator
Version: 0.15.3
Summary: Extended JSON Schema Validator
Home-page: https://github.com/inab/python-extended-json-schema-validator
Author: José Mª Fernández
Author-email: jose.m.fernandez@bsc.es
License: LGPLv2
Project-URL: Bug Tracker, https://github.com/inab/python-extended-json-schema-validator/issues
Classifier: Programming Language :: Python :: 3
Classifier: License :: OSI Approved :: GNU Lesser General Public License v2 (LGPLv2)
Classifier: Operating System :: OS Independent
Requires-Python: >=3.6
License-File: LICENSE
Requires-Dist: ijson
Requires-Dist: jsonschema[format-nongpl] <4.18.0,>=3.0.0
Requires-Dist: jsonpath-ng
Requires-Dist: uritools
Requires-Dist: pyyaml
Requires-Dist: pyxdg
